LICENSE.txt
MANIFEST.in
README.md
setup.cfg
setup.py
automata/__init__.py
automata/automata.py
automata/modules/__init__.py
automata/modules/mod_date.py
automata/modules/mod_day.py
automata/modules/mod_life.py
automata/modules/mod_meaning.py
automata/modules/mod_time.py
python_automata.egg-info/PKG-INFO
python_automata.egg-info/SOURCES.txt
python_automata.egg-info/dependency_links.txt
python_automata.egg-info/requires.txt
python_automata.egg-info/top_level.txt