Metadata-Version: 1.1
Name: python-automata
Version: 0.0.1
Summary: A personal assistant with pluggable modules
Home-page: https://github.com/rahulxxarora/Automata-pip
Author: Rahul Arora
Author-email: coderahul94@gmail.com
License: MIT
Keywords: automata,personal assistant,ML
Platform: UNKNOWN
Classifier: Intended Audience :: Developers
Classifier: License :: OSI Approved :: MIT License
Classifier: Programming Language :: Python
Classifier: Operating System :: POSIX
